kerdokustats.py
kerdokustats-1.0.4.2.dist-info/WHEEL
kerdokustats-1.0.4.2.dist-info/METADATA
kerdokustats-1.0.4.2.dist-info/RECORD
