Metadata-Version: 2.1
Name: kerdokustats
Version: 1.0.4.2
Summary: KerdokuBot Stats
Home-page: https://kerdokuds.ml
Keywords: packaging,stas,ds,discord,kerdoku,kerdokustats,kerdokuds,kerdokubot,Grey Cat
Author: Grey Cat
Requires-Python: >=3.8,<4.0
Classifier: Programming Language :: Python :: 3
Classifier: Programming Language :: Python :: 3.8
Requires-Dist: requests (>=2.24.0,<3.0.0)
